GoBlogZhongwenfanyiFix1/README.md
GoBlogZhongwenfanyiFix1/__init__.py
GoBlogZhongwenfanyiFix1/__main__.py
GoBlogZhongwenfanyiFix1/file.epub
GoBlogZhongwenfanyiFix1/index.html
GoBlogZhongwenfanyiFix1/css/__init__.py
GoBlogZhongwenfanyiFix1/css/annotations.css
GoBlogZhongwenfanyiFix1/css/main.css
GoBlogZhongwenfanyiFix1/css/normalize.css
GoBlogZhongwenfanyiFix1/css/popup.css
GoBlogZhongwenfanyiFix1/font/__init__.py
GoBlogZhongwenfanyiFix1/font/fontello.eot
GoBlogZhongwenfanyiFix1/font/fontello.svg
GoBlogZhongwenfanyiFix1/font/fontello.ttf
GoBlogZhongwenfanyiFix1/font/fontello.woff
GoBlogZhongwenfanyiFix1/img/__init__.py
GoBlogZhongwenfanyiFix1/img/annotator-glyph-sprite.png
GoBlogZhongwenfanyiFix1/img/annotator-icon-sprite.png
GoBlogZhongwenfanyiFix1/img/apple-touch-icon.png
GoBlogZhongwenfanyiFix1/img/cancelfullscreen.png
GoBlogZhongwenfanyiFix1/img/close.png
GoBlogZhongwenfanyiFix1/img/fullscreen.png
GoBlogZhongwenfanyiFix1/img/loader.gif
GoBlogZhongwenfanyiFix1/img/menu-icon.png
GoBlogZhongwenfanyiFix1/img/save.png
GoBlogZhongwenfanyiFix1/img/saved.png
GoBlogZhongwenfanyiFix1/img/settings-s.png
GoBlogZhongwenfanyiFix1/img/settings.png
GoBlogZhongwenfanyiFix1/img/star.png
GoBlogZhongwenfanyiFix1/js/__init__.py
GoBlogZhongwenfanyiFix1/js/epub.js
GoBlogZhongwenfanyiFix1/js/epub.min.js
GoBlogZhongwenfanyiFix1/js/epub.min.map
GoBlogZhongwenfanyiFix1/js/hooks.min.js
GoBlogZhongwenfanyiFix1/js/hooks.min.map
GoBlogZhongwenfanyiFix1/js/reader.js
GoBlogZhongwenfanyiFix1/js/reader.js.map
GoBlogZhongwenfanyiFix1/js/reader.min.js
GoBlogZhongwenfanyiFix1/js/reader.min.map
GoBlogZhongwenfanyiFix1/js/hooks/__init__.py
GoBlogZhongwenfanyiFix1/js/hooks/extensions/__init__.py
GoBlogZhongwenfanyiFix1/js/hooks/extensions/highlight.js
GoBlogZhongwenfanyiFix1/js/libs/__init__.py
GoBlogZhongwenfanyiFix1/js/libs/jquery.min.js
GoBlogZhongwenfanyiFix1/js/libs/localforage.min.js
GoBlogZhongwenfanyiFix1/js/libs/screenfull.js
GoBlogZhongwenfanyiFix1/js/libs/screenfull.min.js
go_blog_zhongwenfanyi_fix1-2025.3.25.0.dist-info/METADATA
go_blog_zhongwenfanyi_fix1-2025.3.25.0.dist-info/WHEEL
go_blog_zhongwenfanyi_fix1-2025.3.25.0.dist-info/entry_points.txt
go_blog_zhongwenfanyi_fix1-2025.3.25.0.dist-info/top_level.txt
go_blog_zhongwenfanyi_fix1-2025.3.25.0.dist-info/RECORD
